[
  { "title": "AWS S3" },
  { "title": "AWS Lambda" },
  { "title": "mongoDB" },
  { "title": "C++" },
  { "title": "AWS SES" },
  { "title": "Contentful" },
  { "title": "Netlify" },
  { "title": "OpenGL ES" },
  { "title": "D3.js" },
  { "title": "SQLite" },
  { "title": "Gatsby" },
  { "title": "CSS3" },
  { "title": "docker" },
  { "title": "AWS DynamoDB" },
  { "title": "HTML5" },
  { "title": "AWS ElasticBeanstalk" },
  { "title": "GraphQL" },
  { "title": "Vue.js" },
  { "title": "AWS EC2" },
  { "title": "Unit testing" },
  { "title": "BABEL" },
  { "title": "Qt" },
  { "title": "CI/CD" },
  { "title": "Swift" },
  { "title": "NodeJS" },
  { "title": "Redux" },
  { "title": "Webpack" },
  { "title": "ReactJS" },
  { "title": "NEXT.JS" },
  { "title": "Objective-C" },
  { "title": "Javascript" },
  { "title": "Serverless" }
]
